[{"title": "Journal", "slug": "journal", "module": "journal", "list_fields": "title,description,entry_date,owner", "search_fields": "", "filter_fields": "", "excel_fields": "", "published": false, "pagelimit": 10, "require_login": false, "allowed_roles": "", "publish_date": null, "expire_date": null, "data_table_name": "", "update_table_name": "", "fields": [{"name": "record_status", "label": "Status", "field_type": "string", "obj_table": null, "obj_field": null, "default": null}, {"name": "id", "label": "ID", "field_type": "integer", "obj_table": null, "obj_field": null, "default": null}, {"name": "title", "label": "Title", "field_type": "string", "obj_table": "", "obj_field": "", "default": ""}, {"name": "description", "label": "Description", "field_type": "text", "obj_table": "", "obj_field": "", "default": ""}, {"name": "owner", "label": "Owner", "field_type": "user", "obj_table": "", "obj_field": "", "default": "output = curuser.id"}, {"name": "entry_date", "label": "Entry Date", "field_type": "datetime", "obj_table": "", "obj_field": "", "default": "output = datetime.datetime.today()"}], "roles": [{"name": "Admin", "role_type": "module", "compare": null}, {"name": "Owner", "role_type": "query", "compare": "owner={{ curuser.id }}"}], "statuses": [{"name": "New", "display_fields": "entry_date,owner,title,description"}], "transitions": [{"name": "new", "display_fields": "", "edit_fields": "title,description,entry_date,owner", "prev_status": null, "next_status": "New", "roles": "Admin", "postpage": ""}]}]